[
  {
    "name": "Rising Moon",
    "url": "https://raw.githubusercontent.com/fcjfior/rhythmloft-cdn-i/main/fantasy/Rising_Moon(chosic.com).mp3",
    "source": "https://www.chosic.com/download-audio/28497/",
    "authors": [
      "RandomMind"
    ]
  },
  {
    "name": "King’s Feast",
    "url": "https://raw.githubusercontent.com/fcjfior/rhythmloft-cdn-i/main/fantasy/Kings_Feast(chosic.com).mp3",
    "source": "https://www.chosic.com/download-audio/28498/",
    "authors": [
      "RandomMind"
    ]
  },
  {
    "name": "The Old Tower Inn",
    "url": "https://raw.githubusercontent.com/fcjfior/rhythmloft-cdn-i/main/fantasy/The_Old_Tower_Inn(chosic.com).mp3",
    "source": "https://www.chosic.com/download-audio/28499/",
    "authors": [
      "RandomMind"
    ]
  },
  {
    "name": "Rejoicing",
    "url": "https://raw.githubusercontent.com/fcjfior/rhythmloft-cdn-i/main/fantasy/Rejoicing(chosic.com).mp3",
    "source": "https://www.chosic.com/download-audio/28500/",
    "authors": [
      "RandomMind"
    ]
  },
  {
    "name": "Fireside Tales",
    "url": "https://raw.githubusercontent.com/fcjfior/rhythmloft-cdn-i/main/fantasy/Fireside-Tales-MP3(chosic.com).mp3",
    "source": "https://www.chosic.com/download-audio/28506/",
    "authors": [
      "Darren Curtis"
    ]
  },
  {
    "name": "Haven Of The Faeries",
    "url": "https://raw.githubusercontent.com/fcjfior/rhythmloft-cdn-i/main/fantasy/Haven-of-the-Faeries-MP3(chosic.com).mp3",
    "source": "https://www.chosic.com/download-audio/28507/",
    "authors": [
      "Darren Curtis"
    ]
  },
  {
    "name": "Over The Plains Of Snow",
    "url": "https://raw.githubusercontent.com/fcjfior/rhythmloft-cdn-i/main/fantasy/Over-the-Plains-of-Snow-MP3(chosic.com).mp3",
    "source": "https://www.chosic.com/download-audio/28511/",
    "authors": [
      "Darren Curtis"
    ]
  },
  {
    "name": "Peace On The Water",
    "url": "https://raw.githubusercontent.com/fcjfior/rhythmloft-cdn-i/main/fantasy/Peace-on-the-Water-MP3(chosic.com).mp3",
    "source": "https://www.chosic.com/download-audio/28512/",
    "authors": [
      "Darren Curtis"
    ]
  },
  {
    "name": "A Time Forgotten",
    "url": "https://raw.githubusercontent.com/fcjfior/rhythmloft-cdn-i/main/fantasy/A-Time-Forgotten-MP3(chosic.com).mp3",
    "source": "https://www.chosic.com/download-audio/28514/",
    "authors": [
      "Darren Curtis"
    ]
  },
  {
    "name": "Ale And Anecdotes",
    "url": "https://raw.githubusercontent.com/fcjfior/rhythmloft-cdn-i/main/fantasy/Ale-and-Anecdotes-MP3(chosic.com).mp3",
    "source": "https://www.chosic.com/download-audio/28515/",
    "authors": [
      "Darren Curtis"
    ]
  },
  {
    "name": "The Bard’s Tale",
    "url": "https://raw.githubusercontent.com/fcjfior/rhythmloft-cdn-i/main/fantasy/The_Bards_Tale(chosic.com).mp3",
    "source": "https://www.chosic.com/download-audio/27015/",
    "authors": [
      "RandomMind"
    ]
  },
  {
    "name": "Market Day",
    "url": "https://raw.githubusercontent.com/fcjfior/rhythmloft-cdn-i/main/fantasy/Market_Day(chosic.com).mp3",
    "source": "https://www.chosic.com/download-audio/27016/",
    "authors": [
      "RandomMind"
    ]
  },
  {
    "name": "Minstrel Dance",
    "url": "https://raw.githubusercontent.com/fcjfior/rhythmloft-cdn-i/main/fantasy/Minstrel_Dance(chosic.com).mp3",
    "source": "https://www.chosic.com/download-audio/27017/",
    "authors": [
      "RandomMind"
    ]
  },
  {
    "name": "Peaceful Forest “Into Oblivion”",
    "url": "https://raw.githubusercontent.com/fcjfior/rhythmloft-cdn-i/main/fantasy/Into-Oblivion(chosic.com).mp3",
    "source": "https://www.chosic.com/download-audio/27972/",
    "authors": [
      "Darren Curtis"
    ]
  },
  {
    "name": "I’m Not What I Thought",
    "url": "https://raw.githubusercontent.com/fcjfior/rhythmloft-cdn-i/main/fantasy/darren-curtis-i-am-not-what-i-thought(chosic.com).mp3",
    "source": "https://www.chosic.com/download-audio/27974/",
    "authors": [
      "Darren Curtis"
    ]
  },
  {
    "name": "Eternal Sleep",
    "url": "https://raw.githubusercontent.com/fcjfior/rhythmloft-cdn-i/main/fantasy/Eternal-Sleep(chosic.com).mp3",
    "source": "https://www.chosic.com/download-audio/28002/",
    "authors": [
      "Darren Curtis"
    ]
  },
  {
    "name": "Lake Of Destiny",
    "url": "https://raw.githubusercontent.com/fcjfior/rhythmloft-cdn-i/main/fantasy/Lake-of-Destiny(chosic.com).mp3",
    "source": "https://www.chosic.com/download-audio/28004/",
    "authors": [
      "Darren Curtis"
    ]
  },
  {
    "name": "Guitar Gentle",
    "url": "https://raw.githubusercontent.com/fcjfior/rhythmloft-cdn-i/main/fantasy/Guitar-Gentle(chosic.com).mp3",
    "source": "https://www.chosic.com/download-audio/29514/",
    "authors": [
      "PeriTune"
    ]
  },
  {
    "name": "Soar",
    "url": "https://raw.githubusercontent.com/fcjfior/rhythmloft-cdn-i/main/fantasy/scott-buckley-soar(chosic.com).mp3",
    "source": "https://www.chosic.com/download-audio/29607/",
    "authors": [
      "Scott Buckley"
    ]
  },
  {
    "name": "Nowhere Land",
    "url": "https://raw.githubusercontent.com/fcjfior/rhythmloft-cdn-i/main/fantasy/Nowhere-Land(chosic.com).mp3",
    "source": "https://www.chosic.com/download-audio/29626/",
    "authors": [
      "Alexander Nakarada"
    ]
  },
  {
    "name": "The Lone Wolf",
    "url": "https://raw.githubusercontent.com/fcjfior/rhythmloft-cdn-i/main/fantasy/The-Lone-Wolf(chosic.com).mp3",
    "source": "https://www.chosic.com/download-audio/29628/",
    "authors": [
      "Alexander Nakarada"
    ]
  },
  {
    "name": "Beyond The Horizon",
    "url": "https://raw.githubusercontent.com/fcjfior/rhythmloft-cdn-i/main/fantasy/Beyond-The-Horizon(chosic.com).mp3",
    "source": "https://www.chosic.com/download-audio/29629/",
    "authors": [
      "Alexander Nakarada"
    ]
  },
  {
    "name": "Carol Of The Bells Celtic Version",
    "url": "https://raw.githubusercontent.com/fcjfior/rhythmloft-cdn-i/main/fantasy/Carol-Of-The-Bells-Celtic-Version(chosic.com).mp3",
    "source": "https://www.chosic.com/download-audio/29630/",
    "authors": [
      "Alexander Nakarada"
    ]
  },
  {
    "name": "Wintersong",
    "url": "https://raw.githubusercontent.com/fcjfior/rhythmloft-cdn-i/main/fantasy/Wintersong(chosic.com).mp3",
    "source": "https://www.chosic.com/download-audio/29631/",
    "authors": [
      "Alexander Nakarada"
    ]
  },
  {
    "name": "Neverland",
    "url": "https://raw.githubusercontent.com/fcjfior/rhythmloft-cdn-i/main/fantasy/Neverland(chosic.com).mp3",
    "source": "https://www.chosic.com/download-audio/29632/",
    "authors": [
      "Alexander Nakarada"
    ]
  },
  {
    "name": "Horsemen Approach",
    "url": "https://raw.githubusercontent.com/fcjfior/rhythmloft-cdn-i/main/fantasy/Horsemen-Approach(chosic.com).mp3",
    "source": "https://www.chosic.com/download-audio/29633/",
    "authors": [
      "Alexander Nakarada ft. Kevin MacLeod"
    ]
  },
  {
    "name": "Dungeons And Dragons",
    "url": "https://raw.githubusercontent.com/fcjfior/rhythmloft-cdn-i/main/fantasy/Dungeons-And-Dragons(chosic.com).mp3",
    "source": "https://www.chosic.com/download-audio/29634/",
    "authors": [
      "Alexander Nakarada"
    ]
  },
  {
    "name": "Towards The Horizon",
    "url": "https://raw.githubusercontent.com/fcjfior/rhythmloft-cdn-i/main/fantasy/Towards-The-Horizon(chosic.com).mp3",
    "source": "https://www.chosic.com/download-audio/29635/",
    "authors": [
      "Alexander Nakarada"
    ]
  },
  {
    "name": "The Northern Path",
    "url": "https://raw.githubusercontent.com/fcjfior/rhythmloft-cdn-i/main/fantasy/The-Northern-Path(chosic.com).mp3",
    "source": "https://www.chosic.com/download-audio/29637/",
    "authors": [
      "Alexander Nakarada"
    ]
  },
  {
    "name": "Until The End",
    "url": "https://raw.githubusercontent.com/fcjfior/rhythmloft-cdn-i/main/fantasy/Until-The-End(chosic.com).mp3",
    "source": "https://www.chosic.com/download-audio/29644/",
    "authors": [
      "Alexander Nakarada"
    ]
  },
  {
    "name": "Leaving For Valhalla",
    "url": "https://raw.githubusercontent.com/fcjfior/rhythmloft-cdn-i/main/fantasy/Leaving-For-Valhalla(chosic.com).mp3",
    "source": "https://www.chosic.com/download-audio/29645/",
    "authors": [
      "Alexander Nakarada"
    ]
  },
  {
    "name": "Sorrow",
    "url": "https://raw.githubusercontent.com/fcjfior/rhythmloft-cdn-i/main/fantasy/Sorrow(chosic.com).mp3",
    "source": "https://www.chosic.com/download-audio/29646/",
    "authors": [
      "Alexander Nakarada"
    ]
  },
  {
    "name": "Bach’s Bouree In Celtic Minor",
    "url": "https://raw.githubusercontent.com/fcjfior/rhythmloft-cdn-i/main/fantasy/Bachs-Bouree-In-Celtic-Minor(chosic.com).mp3",
    "source": "https://www.chosic.com/download-audio/29647/",
    "authors": [
      "Alexander Nakarada"
    ]
  },
  {
    "name": "Nomadic Dawn",
    "url": "https://raw.githubusercontent.com/fcjfior/rhythmloft-cdn-i/main/fantasy/Nomadic-Dawn(chosic.com).mp3",
    "source": "https://www.chosic.com/download-audio/29648/",
    "authors": [
      "Alexander Nakarada"
    ]
  },
  {
    "name": "One Bard Band",
    "url": "https://raw.githubusercontent.com/fcjfior/rhythmloft-cdn-i/main/fantasy/One-Bard-Band(chosic.com).mp3",
    "source": "https://www.chosic.com/download-audio/29651/",
    "authors": [
      "Alexander Nakarada"
    ]
  },
  {
    "name": "Farm",
    "url": "https://raw.githubusercontent.com/fcjfior/rhythmloft-cdn-i/main/fantasy/Farm(chosic.com).mp3",
    "source": "https://www.chosic.com/download-audio/29653/",
    "authors": [
      "Alexander Nakarada"
    ]
  },
  {
    "name": "Planning",
    "url": "https://raw.githubusercontent.com/fcjfior/rhythmloft-cdn-i/main/fantasy/Planning(chosic.com).mp3",
    "source": "https://www.chosic.com/download-audio/29654/",
    "authors": [
      "Alexander Nakarada"
    ]
  },
  {
    "name": "Now We Ride",
    "url": "https://raw.githubusercontent.com/fcjfior/rhythmloft-cdn-i/main/fantasy/Now-We-Ride(chosic.com).mp3",
    "source": "https://www.chosic.com/download-audio/29657/",
    "authors": [
      "Alexander Nakarada"
    ]
  },
  {
    "name": "Highland Song",
    "url": "https://raw.githubusercontent.com/fcjfior/rhythmloft-cdn-i/main/fantasy/Highland-Song(chosic.com).mp3",
    "source": "https://www.chosic.com/download-audio/29658/",
    "authors": [
      "Alexander Nakarada"
    ]
  },
  {
    "name": "Surreal Forest",
    "url": "https://raw.githubusercontent.com/fcjfior/rhythmloft-cdn-i/main/fantasy/04-Meydan-Surreal-Forest(chosic.com).mp3",
    "source": "https://www.chosic.com/download-audio/30330/",
    "authors": [
      "Meydän"
    ]
  },
  {
    "name": "Invocation",
    "url": "https://raw.githubusercontent.com/fcjfior/rhythmloft-cdn-i/main/fantasy/sb_invocation(chosic.com).mp3",
    "source": "https://www.chosic.com/download-audio/57877/",
    "authors": [
      "Scott Buckley"
    ]
  },
  {
    "name": "Enchanted",
    "url": "https://raw.githubusercontent.com/fcjfior/rhythmloft-cdn-i/main/fantasy/Enchanted(chosic.com).mp3",
    "source": "https://www.chosic.com/download-audio/30479/",
    "authors": [
      "Keys of Moon"
    ]
  },
  {
    "name": "Minstrel’s Song",
    "url": "https://raw.githubusercontent.com/fcjfior/rhythmloft-cdn-i/main/fantasy/Minstrels-Song(chosic.com).mp3",
    "source": "https://www.chosic.com/download-audio/30487/",
    "authors": [
      "Keys of Moon"
    ]
  },
  {
    "name": "River Dance",
    "url": "https://raw.githubusercontent.com/fcjfior/rhythmloft-cdn-i/main/fantasy/River-Dance-Folk-Fantasy-Music(chosic.com).mp3",
    "source": "https://www.chosic.com/download-audio/32077/",
    "authors": [
      "Keys of Moon"
    ]
  },
  {
    "name": "Come Out And Play",
    "url": "https://raw.githubusercontent.com/fcjfior/rhythmloft-cdn-i/main/fantasy/Come-Out-And-Play-Remixed-Royalty-Free(chosic.com).mp3",
    "source": "https://www.chosic.com/download-audio/45513/",
    "authors": [
      "Darren Curtis"
    ]
  },
  {
    "name": "A Robust Crew",
    "url": "https://raw.githubusercontent.com/fcjfior/rhythmloft-cdn-i/main/fantasy/a-robust-crew(chosic.com).mp3",
    "source": "https://www.chosic.com/download-audio/45396/",
    "authors": [
      "Darren Curtis"
    ]
  },
  {
    "name": "Echoes Of Home",
    "url": "https://raw.githubusercontent.com/fcjfior/rhythmloft-cdn-i/main/fantasy/EchoesOfHome-chosic.com_.mp3",
    "source": "https://www.chosic.com/download-audio/59912/",
    "authors": [
      "Scott Buckley"
    ]
  },
  {
    "name": "Fantasy Soundscape",
    "url": "https://raw.githubusercontent.com/fcjfior/rhythmloft-cdn-i/main/fantasy/Fantasy_Soundscape-chosic.com_.mp3",
    "source": "https://www.chosic.com/download-audio/59401/",
    "authors": [
      "Alexander Nakarada"
    ]
  },
  {
    "name": "Dream Of A Dream",
    "url": "https://raw.githubusercontent.com/fcjfior/rhythmloft-cdn-i/main/fantasy/Dream_of_a_Dream-chosic.com_.mp3",
    "source": "https://www.chosic.com/download-audio/59400/",
    "authors": [
      "Alexander Nakarada"
    ]
  },
  {
    "name": "Misty Hollow",
    "url": "https://raw.githubusercontent.com/fcjfior/rhythmloft-cdn-i/main/fantasy/Peritune_Misty_Hollow-chosic.com_.mp3",
    "source": "https://www.chosic.com/download-audio/59368/",
    "authors": [
      "PeriTune"
    ]
  },
  {
    "name": "Realm Of Eternal Legends",
    "url": "https://raw.githubusercontent.com/fcjfior/rhythmloft-cdn-i/main/fantasy/Realm_of_Eternal_Legends-chosic.com_.mp3",
    "source": "https://www.chosic.com/download-audio/59061/",
    "authors": [
      "Alexander Nakarada"
    ]
  },
  {
    "name": "Lively Tavern",
    "url": "https://raw.githubusercontent.com/fcjfior/rhythmloft-cdn-i/main/fantasy/Lively_Tavern-chosic.com_.mp3",
    "source": "https://www.chosic.com/download-audio/59059/",
    "authors": [
      "Alexander Nakarada"
    ]
  },
  {
    "name": "Bewitched Forest",
    "url": "https://raw.githubusercontent.com/fcjfior/rhythmloft-cdn-i/main/fantasy/Peritune_Bewitched_Forest-chosic.com_.mp3",
    "source": "https://www.chosic.com/download-audio/58935/",
    "authors": [
      "PeriTune"
    ]
  },
  {
    "name": "Alleyway",
    "url": "https://raw.githubusercontent.com/fcjfior/rhythmloft-cdn-i/main/fantasy/PeriTune_Alleyway-chosic.com_.mp3",
    "source": "https://www.chosic.com/download-audio/58934/",
    "authors": [
      "PeriTune"
    ]
  },
  {
    "name": "Cold Light",
    "url": "https://raw.githubusercontent.com/fcjfior/rhythmloft-cdn-i/main/fantasy/Peritune_Cold_Light-chosic.com_.mp3",
    "source": "https://www.chosic.com/download-audio/58931/",
    "authors": [
      "PeriTune"
    ]
  }
]